arachnid_shield_sdk/__init__.py
arachnid_shield_sdk/api/__init__.py
arachnid_shield_sdk/api/client.py
arachnid_shield_sdk/api/v1.py
arachnid_shield_sdk/models/__init__.py
arachnid_shield_sdk/models/error_detail.py
arachnid_shield_sdk/models/match_details.py
arachnid_shield_sdk/models/media.py
arachnid_shield_sdk/models/media_classification.py
arachnid_shield_sdk/models/scan_media_from_bytes.py
arachnid_shield_sdk/models/scan_media_from_url.py
arachnid_shield_sdk/models/scanned_media.py
arachnid_shield_sdk/models/scanned_pdq.py
arachnid_shield_sdk/models/visual_match_details.py
arachnid_shield_sdk/py.typed
arachnid_shield_sdk-0.2.2.dist-info/LICENSE
arachnid_shield_sdk-0.2.2.dist-info/METADATA
arachnid_shield_sdk-0.2.2.dist-info/WHEEL
arachnid_shield_sdk-0.2.2.dist-info/RECORD
