Metadata-Version: 2.3
Name: arachnid-shield-sdk
Version: 0.2.2
Summary: An SDK to work with the Arachnid Shield API
License: LICENSE
Keywords: arachnid-shield,sdk,arachnid
Author: Aalekh Patel
Author-email: aalekh@protectchildren.ca
Requires-Python: >=3.10,<4.0
Classifier: Development Status :: 4 - Beta
Classifier: License :: Other/Proprietary License
Classifier: Programming Language :: Python :: 3
Classifier: Programming Language :: Python :: 3.10
Classifier: Programming Language :: Python :: 3.11
Classifier: Programming Language :: Python :: 3.12
Classifier: Programming Language :: Python :: 3.13
Requires-Dist: httpx (>=0.18.2)
Project-URL: Documentation, https://shield.projectarachnid.com/
Project-URL: Homepage, https://shield.projectarachnid.com/
Project-URL: Repository, https://github.com/CdnCentreForChildProtection/arachnid-shield-sdk-python/
